split_image/__init__.py
split_image/split.py
split_image-2.0.1.dist-info/LICENSE
split_image-2.0.1.dist-info/METADATA
split_image-2.0.1.dist-info/WHEEL
split_image-2.0.1.dist-info/entry_points.txt
split_image-2.0.1.dist-info/top_level.txt
split_image-2.0.1.dist-info/RECORD
