Metadata-Version: 2.1
Name: split-image
Version: 2.0.1
Summary: A package that lets you quickly split an image into rows and columns (tiles).
Home-page: https://github.com/whiplashoo/split-image
Author: Minas Giannekas
Author-email: contact@whidev.com
Project-URL: Bug Tracker, https://github.com/whiplashoo/split-image/issues
Classifier: Programming Language :: Python :: 3
Classifier: License :: OSI Approved :: MIT License
Classifier: Operating System :: OS Independent
Requires-Python: >=3.6
License-File: LICENSE
